{
  "UserEvents": {
    "vchel": [],
    "Owner": [],
    "d1638316d18f4a1e23a287aaaa12b6c540f704e257a6549bc9a672497ccc934e": [
      {
        "NewName": null,
        "OldName": "StartScreen.ColoredRectangle ColoredRectangleInstance in StartScreen",
        "ElementType": "Screens",
        "EventType": 6,
        "TimestampUtc": "2026-02-13T15:50:30.960258Z"
      },
      {
        "NewName": null,
        "OldName": "StartScreen.Text TextInstance1 in StartScreen",
        "ElementType": "Screens",
        "EventType": 6,
        "TimestampUtc": "2026-02-13T15:50:31.0153976Z"
      },
      {
        "NewName": null,
        "OldName": "StartScreen.Container ContainerInstance in StartScreen",
        "ElementType": "Screens",
        "EventType": 6,
        "TimestampUtc": "2026-02-13T15:50:36.3207121Z"
      },
      {
        "NewName": null,
        "OldName": "StartScreen.ColoredRectangle ColoredRectangleInstance1 in StartScreen",
        "ElementType": "Screens",
        "EventType": 6,
        "TimestampUtc": "2026-02-13T15:50:36.3780853Z"
      },
      {
        "NewName": null,
        "OldName": "StartScreen.ColoredRectangle ColoredRectangleInstance2 in StartScreen",
        "ElementType": "Screens",
        "EventType": 6,
        "TimestampUtc": "2026-02-13T15:50:36.3793562Z"
      },
      {
        "NewName": null,
        "OldName": "StartScreen.ColoredRectangle ColoredRectangleInstance3 in StartScreen",
        "ElementType": "Screens",
        "EventType": 6,
        "TimestampUtc": "2026-02-13T15:50:36.3805519Z"
      },
      {
        "NewName": null,
        "OldName": "StartScreen.ColoredRectangle ColoredRectangleInstance4 in StartScreen",
        "ElementType": "Screens",
        "EventType": 6,
        "TimestampUtc": "2026-02-13T15:50:36.3816227Z"
      },
      {
        "NewName": null,
        "OldName": "StartScreen.Text TextInstance3 in StartScreen",
        "ElementType": "Screens",
        "EventType": 6,
        "TimestampUtc": "2026-02-13T15:50:36.3825972Z"
      },
      {
        "NewName": null,
        "OldName": "StartScreen.Text TextInstance in StartScreen",
        "ElementType": "Screens",
        "EventType": 6,
        "TimestampUtc": "2026-02-13T15:50:42.037026Z"
      },
      {
        "NewName": null,
        "OldName": "StartScreen.Text TextInstance2 in StartScreen",
        "ElementType": "Screens",
        "EventType": 6,
        "TimestampUtc": "2026-02-13T15:50:42.03798Z"
      },
      {
        "NewName": null,
        "OldName": "StartScreen.Circle CircleInstance in StartScreen",
        "ElementType": "Screens",
        "EventType": 6,
        "TimestampUtc": "2026-02-13T15:50:42.0387441Z"
      },
      {
        "NewName": null,
        "OldName": "StartScreen.Text TextInstance7 in StartScreen",
        "ElementType": "Screens",
        "EventType": 6,
        "TimestampUtc": "2026-02-13T15:50:42.0394942Z"
      },
      {
        "NewName": null,
        "OldName": "StartScreen.Sprite SpriteInstance1 in StartScreen",
        "ElementType": "Screens",
        "EventType": 6,
        "TimestampUtc": "2026-02-13T15:50:42.0408173Z"
      },
      {
        "NewName": null,
        "OldName": "StartScreen.Sprite SpriteInstance2 in StartScreen",
        "ElementType": "Screens",
        "EventType": 6,
        "TimestampUtc": "2026-02-13T15:50:42.041936Z"
      },
      {
        "NewName": null,
        "OldName": "StartScreen.Text TextInstance8 in StartScreen",
        "ElementType": "Screens",
        "EventType": 6,
        "TimestampUtc": "2026-02-13T15:50:42.0427768Z"
      },
      {
        "NewName": null,
        "OldName": "StartScreen.NineSlice NineSliceInstance in StartScreen",
        "ElementType": "Screens",
        "EventType": 6,
        "TimestampUtc": "2026-02-13T15:50:42.0433612Z"
      },
      {
        "NewName": null,
        "OldName": "StartScreen.Polygon PolygonInstance in StartScreen",
        "ElementType": "Screens",
        "EventType": 6,
        "TimestampUtc": "2026-02-13T15:50:42.0439896Z"
      },
      {
        "NewName": null,
        "OldName": "StartScreen.Rectangle RectangleInstance in StartScreen",
        "ElementType": "Screens",
        "EventType": 6,
        "TimestampUtc": "2026-02-13T15:50:42.0447188Z"
      },
      {
        "NewName": null,
        "OldName": "StartScreen.Sprite SpriteInstance in StartScreen",
        "ElementType": "Screens",
        "EventType": 6,
        "TimestampUtc": "2026-02-13T15:50:42.045429Z"
      },
      {
        "NewName": null,
        "OldName": "StartScreen.Container ContainerInstance1 in StartScreen",
        "ElementType": "Screens",
        "EventType": 6,
        "TimestampUtc": "2026-02-13T15:50:42.046459Z"
      },
      {
        "NewName": null,
        "OldName": "StartScreen.ComponentWithExposedVariable ComponentWithExposedVariableInstance in StartScreen",
        "ElementType": "Screens",
        "EventType": 6,
        "TimestampUtc": "2026-02-13T15:50:42.0472844Z"
      },
      {
        "NewName": null,
        "OldName": "StartScreen.Text TextInstance4 in StartScreen",
        "ElementType": "Screens",
        "EventType": 6,
        "TimestampUtc": "2026-02-13T15:50:45.5987158Z"
      },
      {
        "NewName": null,
        "OldName": "StartScreen.Text TextInstance5 in StartScreen",
        "ElementType": "Screens",
        "EventType": 6,
        "TimestampUtc": "2026-02-13T15:50:45.6104888Z"
      },
      {
        "NewName": null,
        "OldName": "StartScreen.Text TextInstance6 in StartScreen",
        "ElementType": "Screens",
        "EventType": 6,
        "TimestampUtc": "2026-02-13T15:50:45.6113846Z"
      },
      {
        "NewName": null,
        "OldName": "StartScreen.Text TextInstance9 in StartScreen",
        "ElementType": "Screens",
        "EventType": 6,
        "TimestampUtc": "2026-02-13T15:50:45.6127504Z"
      },
      {
        "NewName": "StartScreen.TextInstance",
        "OldName": null,
        "ElementType": "Screens",
        "EventType": 5,
        "TimestampUtc": "2026-02-13T15:50:50.4367979Z"
      }
    ]
  }
}